{
  "type": "FeatureCollection",
  "name": "destinations",
  "crs": {
    "type": "name",
    "properties": {
      "name": "urn:ogc:def:crs:OGC:1.3:CRS84"
    }
  },
  "features": [
    {
      "type": "Feature",
      "properties": {
        "name": "Hamburg",
        "type": "port"
      },
      "geometry": {
        "type": "Point",
        "coordinates": [
          9.993682,
          53.551085
        ]
      }
    }
  ]
}